{"time":"6/22/2026, 9:56:48 AM","logs":[{"time":"6/22/2026, 9:56:48 AM","type":"TPEX","status":"OK","detail":"櫃買資料擷取 2026/06/18 成功: 櫃買指數 447.06, 漲跌: 13.72"},{"time":"6/22/2026, 9:56:46 AM","type":"TPEX","status":"FETCHING","detail":"正在從 TPEX API 擷取 2026/06/18 櫃買數據 (嘗試第 1 天)..."},{"time":"6/22/2026, 9:56:46 AM","type":"TWSE","status":"OK","detail":"大盤資料擷取 20260618 成功: 加權指數 46465.2, 漲跌: 587.81"},{"time":"6/22/2026, 9:56:44 AM","type":"TWSE","status":"FETCHING","detail":"正在從 TWSE API 擷取 20260618 大盤數據 (嘗試第 1 天)..."},{"time":"6/22/2026, 2:22:06 AM","type":"TPEX","status":"OK","detail":"櫃買資料擷取 2026/06/18 成功: 櫃買指數 447.06, 漲跌: 13.72"},{"time":"6/22/2026, 2:22:05 AM","type":"TPEX","status":"FETCHING","detail":"正在從 TPEX API 擷取 2026/06/18 櫃買數據 (嘗試第 1 天)..."},{"time":"6/22/2026, 2:22:05 AM","type":"TPEX","status":"OK","detail":"櫃買資料擷取 2026/06/18 成功: 櫃買指數 447.06, 漲跌: 13.72"},{"time":"6/22/2026, 2:22:04 AM","type":"TWSE","status":"OK","detail":"大盤資料擷取 20260618 成功: 加權指數 46465.2, 漲跌: 587.81"},{"time":"6/22/2026, 2:22:04 AM","type":"TWSE","status":"FETCHING","detail":"正在從 TWSE API 擷取 20260618 大盤數據 (嘗試第 1 天)..."},{"time":"6/22/2026, 2:22:04 AM","type":"TWSE","status":"OK","detail":"大盤資料擷取 20260618 成功: 加權指數 46465.2, 漲跌: 587.81"},{"time":"6/22/2026, 2:22:04 AM","type":"TPEX","status":"FETCHING","detail":"正在從 TPEX API 擷取 2026/06/18 櫃買數據 (嘗試第 1 天)..."},{"time":"6/22/2026, 2:22:04 AM","type":"TWSE","status":"FETCHING","detail":"正在從 TWSE API 擷取 20260618 大盤數據 (嘗試第 1 天)..."},{"time":"6/22/2026, 2:08:36 AM","type":"TPEX","status":"OK","detail":"櫃買資料擷取 2026/06/18 成功: 櫃買指數 447.06, 漲跌: 13.72"},{"time":"6/22/2026, 2:08:35 AM","type":"TWSE","status":"OK","detail":"大盤資料擷取 20260618 成功: 加權指數 46465.2, 漲跌: 587.81"},{"time":"6/22/2026, 2:08:35 AM","type":"TWSE","status":"FETCHING","detail":"正在從 TWSE API 擷取 20260618 大盤數據 (嘗試第 1 天)..."},{"time":"6/22/2026, 2:08:35 AM","type":"TWSE","status":"OK","detail":"大盤資料擷取 20260618 成功: 加權指數 46465.2, 漲跌: 587.81"},{"time":"6/22/2026, 2:08:35 AM","type":"TPEX","status":"OK","detail":"櫃買資料擷取 2026/06/18 成功: 櫃買指數 447.06, 漲跌: 13.72"},{"time":"6/22/2026, 2:08:34 AM","type":"TPEX","status":"FETCHING","detail":"正在從 TPEX API 擷取 2026/06/18 櫃買數據 (嘗試第 1 天)..."},{"time":"6/22/2026, 2:08:34 AM","type":"TPEX","status":"OK","detail":"櫃買資料擷取 2026/06/18 成功: 櫃買指數 447.06, 漲跌: 13.72"},{"time":"6/22/2026, 2:08:33 AM","type":"TWSE","status":"FETCHING","detail":"正在從 TWSE API 擷取 20260618 大盤數據 (嘗試第 1 天)..."},{"time":"6/22/2026, 2:08:33 AM","type":"TPEX","status":"FETCHING","detail":"正在從 TPEX API 擷取 2026/06/18 櫃買數據 (嘗試第 1 天)..."},{"time":"6/22/2026, 2:08:33 AM","type":"TPEX","status":"OK","detail":"櫃買資料擷取 2026/06/18 成功: 櫃買指數 447.06, 漲跌: 13.72"},{"time":"6/22/2026, 2:08:33 AM","type":"TPEX","status":"FETCHING","detail":"正在從 TPEX API 擷取 2026/06/18 櫃買數據 (嘗試第 1 天)..."},{"time":"6/22/2026, 2:08:33 AM","type":"TPEX","status":"FETCHING","detail":"正在從 TPEX API 擷取 2026/06/18 櫃買數據 (嘗試第 1 天)..."},{"time":"6/22/2026, 2:08:33 AM","type":"TPEX","status":"OK","detail":"櫃買資料擷取 2026/06/18 成功: 櫃買指數 447.06, 漲跌: 13.72"},{"time":"6/22/2026, 2:08:30 AM","type":"TPEX","status":"FETCHING","detail":"正在從 TPEX API 擷取 2026/06/18 櫃買數據 (嘗試第 1 天)..."},{"time":"6/22/2026, 2:08:30 AM","type":"TPEX","status":"OK","detail":"櫃買資料擷取 2026/06/18 成功: 櫃買指數 447.06, 漲跌: 13.72"},{"time":"6/22/2026, 2:08:28 AM","type":"TWSE","status":"OK","detail":"大盤資料擷取 20260618 成功: 加權指數 46465.2, 漲跌: 587.81"},{"time":"6/22/2026, 2:08:28 AM","type":"TWSE","status":"FETCHING","detail":"正在從 TWSE API 擷取 20260618 大盤數據 (嘗試第 1 天)..."},{"time":"6/22/2026, 2:08:28 AM","type":"TWSE","status":"OK","detail":"大盤資料擷取 20260618 成功: 加權指數 46465.2, 漲跌: 587.81"},{"time":"6/22/2026, 2:08:27 AM","type":"TWSE","status":"FETCHING","detail":"正在從 TWSE API 擷取 20260618 大盤數據 (嘗試第 1 天)..."},{"time":"6/22/2026, 2:08:25 AM","type":"TWSE","status":"OK","detail":"大盤資料擷取 20260618 成功: 加權指數 46465.2, 漲跌: 587.81"},{"time":"6/22/2026, 2:08:25 AM","type":"TWSE","status":"FETCHING","detail":"正在從 TWSE API 擷取 20260618 大盤數據 (嘗試第 1 天)..."},{"time":"6/22/2026, 2:08:25 AM","type":"TWSE","status":"OK","detail":"大盤資料擷取 20260618 成功: 加權指數 46465.2, 漲跌: 587.81"},{"time":"6/22/2026, 2:08:25 AM","type":"TPEX","status":"FETCHING","detail":"正在從 TPEX API 擷取 2026/06/18 櫃買數據 (嘗試第 1 天)..."},{"time":"6/22/2026, 2:08:25 AM","type":"TWSE","status":"FETCHING","detail":"正在從 TWSE API 擷取 20260618 大盤數據 (嘗試第 1 天)..."},{"time":"6/22/2026, 2:08:25 AM","type":"TPEX","status":"OK","detail":"櫃買資料擷取 2026/06/18 成功: 櫃買指數 447.06, 漲跌: 13.72"},{"time":"6/22/2026, 2:08:23 AM","type":"TWSE","status":"OK","detail":"大盤資料擷取 20260618 成功: 加權指數 46465.2, 漲跌: 587.81"},{"time":"6/22/2026, 2:08:23 AM","type":"TWSE","status":"FETCHING","detail":"正在從 TWSE API 擷取 20260618 大盤數據 (嘗試第 1 天)..."},{"time":"6/22/2026, 2:08:23 AM","type":"TWSE","status":"OK","detail":"大盤資料擷取 20260618 成功: 加權指數 46465.2, 漲跌: 587.81"},{"time":"6/22/2026, 2:08:22 AM","type":"TPEX","status":"FETCHING","detail":"正在從 TPEX API 擷取 2026/06/18 櫃買數據 (嘗試第 1 天)..."},{"time":"6/22/2026, 2:08:22 AM","type":"TWSE","status":"FETCHING","detail":"正在從 TWSE API 擷取 20260618 大盤數據 (嘗試第 1 天)..."}],"dbConnected":true}